pandas_batcher/__init__.py
pandas_batcher/pandas_batcher.py
pandas_batcher-0.1.6.dist-info/METADATA
pandas_batcher-0.1.6.dist-info/WHEEL
pandas_batcher-0.1.6.dist-info/licenses/LICENCE
pandas_batcher-0.1.6.dist-info/RECORD
